Metadata-Version: 2.1
Name: shobdohash
Version: 1.0.3
Summary: Phonetically compare Bengali words
Home-page: https://github.com/banglakit/shobdohash
Author: The BanglaKit Project and Contributors
Author-email: contact@banglakit.org
License: MIT
Platform: UNKNOWN
Classifier: Development Status :: 4 - Beta
Classifier: Natural Language :: Bengali
Classifier: License :: OSI Approved :: MIT License
Classifier: Programming Language :: Python :: 3
Classifier: Programming Language :: Python :: 3.5
Classifier: Programming Language :: Python :: 3.6
Classifier: Programming Language :: Python :: 3.7
Classifier: Programming Language :: Python :: 3.8
Requires-Python: >=3.5
